Conf/__init__.py
Conf/test_configVars.py
Pages/GateCls.py
Pages/IndexCls.py
Pages/OnlineAssessmentCls.py
Pages/OverviewCls.py
Pages/ProjectRegisterCls.py
Pages/RegisterCls.py
Pages/ThreadviewCls.py
Pages/__init__.py
Pages/ccs_projectsManagementCls.py
Pages/newWBSelementCls.py
Pages/persProfileCls.py
RunSetups/__init__.py
RunSetups/test_ini_1_createTables.py
RunSetups/test_ini_2_registerSuperadmin.py
RunSetups/test_ini_3_1stProjectSetup.py
RunSetups/test_ini_4_4ProjectsSetup.py
Start/__init__.py
Start/__main__.py
Start/ccs-setuptest.py
Start/ccssetuptest.py
Start/starterclass.py
Tests/__init__.py
Tests/test_loginCreateProjectCreateWBS.py
Tests/test_loginMakePosts.py
Tests/test_loginPersProfileComplete.py
ccs_setuptest_v1-1.1.1.dist-info/LICENSE
ccs_setuptest_v1-1.1.1.dist-info/METADATA
ccs_setuptest_v1-1.1.1.dist-info/WHEEL
ccs_setuptest_v1-1.1.1.dist-info/entry_points.txt
ccs_setuptest_v1-1.1.1.dist-info/top_level.txt
ccs_setuptest_v1-1.1.1.dist-info/RECORD
